nmr_sims/__init__.py
nmr_sims/__main__.py
nmr_sims/_operators.py
nmr_sims/_sanity.py
nmr_sims/_version.py
nmr_sims/nuclei.py
nmr_sims/spin_system.py
nmr_sims/experiments/__init__.py
nmr_sims/experiments/cosy.py
nmr_sims/experiments/hsqc.py
nmr_sims/experiments/jres.py
nmr_sims/experiments/pa.py
nmr_sims-0.0.6.dist-info/LICENSE
nmr_sims-0.0.6.dist-info/METADATA
nmr_sims-0.0.6.dist-info/WHEEL
nmr_sims-0.0.6.dist-info/top_level.txt
nmr_sims-0.0.6.dist-info/RECORD
