Metadata-Version: 2.1
Name: nmr-sims
Version: 0.0.6
Summary: A package for running basic NMR simulations.
Home-page: https://github.com/5hulse/nmr_sims
Author: Simon Hulse
Author-email: simonhulse@protonmail.com
License: UNKNOWN
Platform: UNKNOWN
Requires-Python: >=3.8
License-File: LICENSE
Requires-Dist: matplotlib
Requires-Dist: numpy
Requires-Dist: scipy
Requires-Dist: networkx
